macrokit/__init__.py
macrokit/_symbol.py
macrokit/_validator.py
macrokit/ast.py
macrokit/expression.py
macrokit/head.py
macrokit/macro.py
macrokit/mock.py
macrokit/py.typed
macrokit/type_map.py
macrokit/utils.py
macrokit/ipython/__init__.py
macrokit/ipython/magic.py
macrokit/julia/__init__.py
macrokit/julia/translate.py
macro_kit-0.4.10.dist-info/METADATA
macro_kit-0.4.10.dist-info/WHEEL
macro_kit-0.4.10.dist-info/licenses/LICENSE
macro_kit-0.4.10.dist-info/RECORD
