Metadata-Version: 2.4
Name: macro-kit
Version: 0.4.10
Summary: Macro recording and metaprogramming in Python
Project-URL: Download, https://github.com/hanjinliu/macro-kit
Author-email: Hanjin Liu <liuhanjin.sc@gmail.com>
License: BSD 3-Clause License
License-File: LICENSE
Classifier: Programming Language :: Python
Classifier: Programming Language :: Python :: 3
Classifier: Programming Language :: Python :: 3.9
Classifier: Programming Language :: Python :: 3.10
Classifier: Programming Language :: Python :: 3.11
Classifier: Programming Language :: Python :: 3.12
Classifier: Programming Language :: Python :: 3.13
Requires-Python: >=3.9
Requires-Dist: typing-extensions
Provides-Extra: testing
Requires-Dist: numpy>=1.21.0; extra == 'testing'
Requires-Dist: pandas>=1.3.0; extra == 'testing'
Requires-Dist: pytest>=6.2.0; extra == 'testing'
